lab_partner_utils/__init__.py
lab_partner_utils/cli_command_factory.py
lab_partner_utils/command_builder.py
lab_partner_utils/commands.py
lab_partner_utils/kernel_launcher.py
lab_partner_utils/utils.py
lab_partner_utils/command_sets/git_release.py
lab_partner_utils-0.7.78.dist-info/LICENSE.md
lab_partner_utils-0.7.78.dist-info/METADATA
lab_partner_utils-0.7.78.dist-info/WHEEL
lab_partner_utils-0.7.78.dist-info/entry_points.txt
lab_partner_utils-0.7.78.dist-info/top_level.txt
lab_partner_utils-0.7.78.dist-info/RECORD
