Metadata-Version: 2.1
Name: lab-partner-utils
Version: 0.7.78
Summary: Utilities used to embed Lab Partner into python projects
Author-email: Anthony Schexnaildre <aps@enclarify.com>
Maintainer-email: Anthony Schexnaildre <aps@enclarify.com>
License: # Released under MIT License
Project-URL: homepage, https://github.com/enclarify/lab-partner
Keywords: developer,tools,docker
Classifier: Programming Language :: Python :: 3
Classifier: License :: OSI Approved :: MIT License
Classifier: Operating System :: OS Independent
Classifier: Development Status :: 4 - Beta
Classifier: Intended Audience :: Developers
Classifier: Topic :: Software Development
Requires-Python: >=3.8
License-File: LICENSE.md
Requires-Dist: pytz ==2022.7.1
Requires-Dist: click ==8.1.3
Requires-Dist: docker ==6.0.1
Requires-Dist: importlib-metadata ==6.0.0
Requires-Dist: astpretty ==2.1.0
Requires-Dist: ipykernel ==6.21.2
Requires-Dist: docstring-parser ==0.15
Requires-Dist: python-dotenv ==1.0.0
Requires-Dist: GitPython ==3.1.31
Requires-Dist: tomli >=1.1.0 ; python_version < "3.11"
Provides-Extra: test
Requires-Dist: pytest ==7.2.2 ; extra == 'test'
